README.txt
setup.py
docs/HISTORY.txt
pp/__init__.py
pp.demo.egg-info/PKG-INFO
pp.demo.egg-info/SOURCES.txt
pp.demo.egg-info/dependency_links.txt
pp.demo.egg-info/entry_points.txt
pp.demo.egg-info/namespace_packages.txt
pp.demo.egg-info/not-zip-safe
pp.demo.egg-info/requires.txt
pp.demo.egg-info/top_level.txt
pp/demo/__init__.py
pp/demo/configure.zcml
pp/demo/browser/__init__.py
pp/demo/browser/configure.zcml
pp/demo/browser/demo.py
pp/demo/browser/out
pp/demo/browser/leitlinie/index.html
pp/demo/browser/leitlinie/tmp019qfg.jpeg
pp/demo/browser/leitlinie/tmp1FJmX3.jpeg
pp/demo/browser/leitlinie/tmp2g8txv.jpeg
pp/demo/browser/leitlinie/tmp3_PTPr.jpeg
pp/demo/browser/leitlinie/tmp3e0F_g.jpeg
pp/demo/browser/leitlinie/tmp56jhEb.jpeg
pp/demo/browser/leitlinie/tmp5XVhAT.jpeg
pp/demo/browser/leitlinie/tmp7C3YIN.jpeg
pp/demo/browser/leitlinie/tmp7sQ67w.jpeg
pp/demo/browser/leitlinie/tmp8HRQm3.jpeg
pp/demo/browser/leitlinie/tmp8JvtIa.jpeg
pp/demo/browser/leitlinie/tmp8LC5LT.jpeg
pp/demo/browser/leitlinie/tmpAcFAOf.jpeg
pp/demo/browser/leitlinie/tmpDfe5_Y.jpeg
pp/demo/browser/leitlinie/tmpDtOJE0.jpeg
pp/demo/browser/leitlinie/tmpEMGUmY.jpeg
pp/demo/browser/leitlinie/tmpGzX15U.jpeg
pp/demo/browser/leitlinie/tmpIVspLY.jpeg
pp/demo/browser/leitlinie/tmpJYSlP1.jpeg
pp/demo/browser/leitlinie/tmpJmZLPY.jpeg
pp/demo/browser/leitlinie/tmpJz34qG.jpeg
pp/demo/browser/leitlinie/tmpK1ZJZJ.jpeg
pp/demo/browser/leitlinie/tmpKbD5z7.jpeg
pp/demo/browser/leitlinie/tmpKe3xMc.jpeg
pp/demo/browser/leitlinie/tmpMAOAWM.jpeg
pp/demo/browser/leitlinie/tmpNKuiPx.jpeg
pp/demo/browser/leitlinie/tmpOGidmO.jpeg
pp/demo/browser/leitlinie/tmpPBnAgM.jpeg
pp/demo/browser/leitlinie/tmpPBpmaH.jpeg
pp/demo/browser/leitlinie/tmpQ9txMy.jpeg
pp/demo/browser/leitlinie/tmpRBX05O.jpeg
pp/demo/browser/leitlinie/tmpS5ROW6.jpeg
pp/demo/browser/leitlinie/tmpSB64fM.jpeg
pp/demo/browser/leitlinie/tmpT8Cd51.jpeg
pp/demo/browser/leitlinie/tmpTN1HnM.jpeg
pp/demo/browser/leitlinie/tmpUSvjSc.jpeg
pp/demo/browser/leitlinie/tmpWO5jsY.jpeg
pp/demo/browser/leitlinie/tmpWrCINj.jpeg
pp/demo/browser/leitlinie/tmpXk2yzx.jpeg
pp/demo/browser/leitlinie/tmpXoqYK9.jpeg
pp/demo/browser/leitlinie/tmpYzmz_l.jpeg
pp/demo/browser/leitlinie/tmpZwmG2q.jpeg
pp/demo/browser/leitlinie/tmp_DAzPn.jpeg
