Metadata-Version: 1.0
Name: pp.demo
Version: 1.5
Summary: pp.demo
Home-page: http://svn.plone.org/svn/collective/
Author: UNKNOWN
Author-email: UNKNOWN
License: GPL
Platform: UNKNOWN
Classifier: Programming Language :: Python
